{
  "gitSyncId": "6953f299cfc2b01310fb5350_1ac2ba86-5a5b-473c-a411-f7b6d6f80b9f",
  "id": "Start_JSObject_SetDate.setDate",
  "pluginId": "js-plugin",
  "pluginType": "JS",
  "unpublishedAction": {
    "actionConfiguration": {
      "encodeParamsToggle": true,
      "jsArguments": [],
      "paginationType": "NONE",
      "timeoutInMillisecond": 10000
    },
    "collectionId": "Start_JSObject_SetDate",
    "confirmBeforeExecute": false,
    "datasource": {
      "isAutoGenerated": false,
      "name": "UNUSED_DATASOURCE",
      "pluginId": "js-plugin"
    },
    "dynamicBindingPathList": [
      {
        "key": "body"
      }
    ],
    "fullyQualifiedName": "JSObject_SetDate.setDate",
    "name": "setDate",
    "pageId": "Start",
    "runBehaviour": "MANUAL",
    "userSetOnLoad": false
  }
}